firebaseauth_py/__init__.py
firebaseauth_py/errors.py
firebaseauth_py/firebase_auth.py
firebaseauth_py-0.0.3.dist-info/LICENSE
firebaseauth_py-0.0.3.dist-info/WHEEL
firebaseauth_py-0.0.3.dist-info/METADATA
firebaseauth_py-0.0.3.dist-info/RECORD
