Metadata-Version: 2.1
Name: firebaseauth-py
Version: 0.0.3
Summary: Unofficial API wrapper for Firebase Auth's REST API
Author: Justin Chiou
Author-email: chiou.kai@gmail.com
Requires-Python: >=3.10,<4.0
Classifier: Programming Language :: Python :: 3
Classifier: Programming Language :: Python :: 3.10
Requires-Dist: build (>=0.8.0,<0.9.0)
Requires-Dist: requests (>=2.28.0,<3.0.0)
Requires-Dist: twine (>=4.0.1,<5.0.0)
